eero/__init__.py
eero/__main__.py
eero/client.py
eero/const.py
eero/exceptions.py
eero/logging.py
eero/py.typed
eero/api/__init__.py
eero/api/ac_compat.py
eero/api/activity.py
eero/api/auth.py
eero/api/auth_storage.py
eero/api/backup.py
eero/api/base.py
eero/api/blacklist.py
eero/api/burst_reporters.py
eero/api/devices.py
eero/api/diagnostics.py
eero/api/dns.py
eero/api/eeros.py
eero/api/forwards.py
eero/api/insights.py
eero/api/networks.py
eero/api/ouicheck.py
eero/api/password.py
eero/api/profiles.py
eero/api/reservations.py
eero/api/routing.py
eero/api/schedule.py
eero/api/security.py
eero/api/settings.py
eero/api/sqm.py
eero/api/support.py
eero/api/thread.py
eero/api/transfer.py
eero/api/updates.py
eero_api-4.0.1.dist-info/licenses/LICENSE
eero_api-4.0.1.dist-info/METADATA
eero_api-4.0.1.dist-info/WHEEL
eero_api-4.0.1.dist-info/top_level.txt
eero_api-4.0.1.dist-info/RECORD
