Metadata-Version: 2.4
Name: eero-api
Version: 4.0.1
Summary: Modern async Python client for Eero network management
Author: Eero API Contributors
Maintainer: Eero API Contributors
License: MIT
Project-URL: Homepage, https://github.com/fulviofreitas/eero-api
Project-URL: Documentation, https://github.com/fulviofreitas/eero-api/wiki
Project-URL: Repository, https://github.com/fulviofreitas/eero-api
Project-URL: Changelog, https://github.com/fulviofreitas/eero-api/blob/master/CHANGELOG.md
Project-URL: Issues, https://github.com/fulviofreitas/eero-api/issues
Keywords: eero,mesh-wifi,wifi,network,async,asyncio,home-automation,smart-home,api-client,iot
Classifier: Development Status :: 4 - Beta
Classifier: Intended Audience :: Developers
Classifier: Intended Audience :: System Administrators
Classifier: License :: OSI Approved :: MIT License
Classifier: Operating System :: OS Independent
Classifier: Programming Language :: Python :: 3
Classifier: Programming Language :: Python :: 3.12
Classifier: Programming Language :: Python :: 3.13
Classifier: Programming Language :: Python :: 3.14
Classifier: Topic :: Home Automation
Classifier: Topic :: Internet
Classifier: Topic :: Software Development :: Libraries
Classifier: Topic :: Software Development :: Libraries :: Python Modules
Classifier: Topic :: System :: Networking
Classifier: Typing :: Typed
Classifier: Framework :: AsyncIO
Requires-Python: >=3.12
License-File: LICENSE
Requires-Dist: aiohttp>=3.8.0
Requires-Dist: pydantic>=2.0.0
Requires-Dist: keyring>=23.0.0
Provides-Extra: dev
Requires-Dist: pytest>=7.0.0; extra == "dev"
Requires-Dist: pytest-asyncio>=0.21.0; extra == "dev"
Requires-Dist: pytest-cov>=4.0.0; extra == "dev"
Requires-Dist: black>=23.0.0; extra == "dev"
Requires-Dist: isort>=5.12.0; extra == "dev"
Requires-Dist: mypy>=1.0.0; extra == "dev"
Requires-Dist: ruff>=0.1.0; extra == "dev"
Requires-Dist: rich>=13.0.0; extra == "dev"
Requires-Dist: click>=8.0.0; extra == "dev"
Requires-Dist: commitizen>=3.0.0; extra == "dev"
Dynamic: license-file
